csmap/__init__.py
csmap/__main__.py
csmap/calc.py
csmap/color.py
csmap/process.py
csmap_py-0.1.4.dist-info/METADATA
csmap_py-0.1.4.dist-info/WHEEL
csmap_py-0.1.4.dist-info/entry_points.txt
csmap_py-0.1.4.dist-info/RECORD
