Metadata-Version: 2.1
Name: csmap-py
Version: 0.1.4
Summary: 
License: MIT
Author: MIERUNE Inc.
Author-email: info@mierune.co.jp
Requires-Python: >=3.10,<4.0
Classifier: License :: OSI Approved :: MIT License
Classifier: Programming Language :: Python :: 3
Classifier: Programming Language :: Python :: 3.10
Classifier: Programming Language :: Python :: 3.11
Classifier: Programming Language :: Python :: 3.12
Requires-Dist: numpy (>=1.26.2,<2.0.0)
Requires-Dist: rasterio (>=1.3.9,<2.0.0)
